pdbp.py
pdbp-1.8.0.dist-info/licenses/LICENSE
pdbp-1.8.0.dist-info/METADATA
pdbp-1.8.0.dist-info/WHEEL
pdbp-1.8.0.dist-info/top_level.txt
pdbp-1.8.0.dist-info/RECORD
